pyefriend/__init__.py
pyefriend/api.py
pyefriend/connection.py
pyefriend/const.py
pyefriend/exceptions.py
pyefriend/helper.py
pyefriend/log.py
rebalancing/__init__.py
rebalancing/__main__.py
rebalancing/config.py
rebalancing/config.template.yml
rebalancing/exceptions.py
rebalancing/settings.py
rebalancing/data/init_data_domestic.csv
rebalancing/data/init_data_overseas.csv
rebalancing/models/__init__.py
rebalancing/models/base.py
rebalancing/models/portfolio.py
rebalancing/models/product.py
rebalancing/process/__init__.py
rebalancing/process/db.py
rebalancing/process/executor.py
rebalancing/utils/__init__.py
rebalancing/utils/const.py
rebalancing/utils/log.py
rebalancing/utils/orm_helper.py
rebalancing/utils/tool.py
pyefriend-1.0.1.dist-info/LICENSE
pyefriend-1.0.1.dist-info/METADATA
pyefriend-1.0.1.dist-info/WHEEL
pyefriend-1.0.1.dist-info/entry_points.txt
pyefriend-1.0.1.dist-info/top_level.txt
pyefriend-1.0.1.dist-info/RECORD
