Metadata-Version: 2.1
Name: pyefriend
Version: 1.0.1
Summary: Python API link to 'efriend expert'
Home-page: https://github.com/softyoungha
Author: Youngha Park
Author-email: proyoungha@naver.com
License: MIT
Keywords: pyefriend,rebalancing,efriend-expert
Platform: UNKNOWN
Requires-Python: >=3
License-File: LICENSE
Requires-Dist: setuptools (==58.5.3)
Requires-Dist: wheel (==0.37.0)
Requires-Dist: pyyaml (==6.0)
Requires-Dist: requests (==2.26.0)
Requires-Dist: PyQt5 (==5.15.6)
Requires-Dist: ipython (==7.29.0)
Requires-Dist: jupyter (==1.0.0)
Requires-Dist: notebook (==6.4.5)
Requires-Dist: pywinpty (<1,>=0.5)
Requires-Dist: numpy (==1.21.4)
Requires-Dist: pandas (==1.3.4)
Requires-Dist: sqlalchemy (==1.4.26)
